{
  "name": "enhanced-logging",
  "description": "Enhanced logging with Elasticsearch integration and metrics",
  "deps": {
    "@elastic/elasticsearch": "^8.10.0",
    "prom-client": "^15.0.0",
    "express-prom-bundle": "^7.0.0"
  },
  "devDeps": {},
  "env": [
    "ELASTICSEARCH_URL",
    "METRICS_ENABLED",
    "METRICS_PORT"
  ],
  "filesPath": "files",
  "conflicts": [],
  "inject": {
    "src/app.module.ts": {
      "import": ["import { EnhancedLoggingModule } from './common/enhanced-logging/enhanced-logging.module';"],
      "register": ["EnhancedLoggingModule"]
    }
  },
  "postInstall": []
}